dreamai_ray/__init__.py
dreamai_ray/_modidx.py
dreamai_ray/imports.py
dreamai_ray/mapper.py
dreamai_ray/redis_kv_store.py
dreamai_ray/utils.py
dreamai_ray/index/__init__.py
dreamai_ray/index/core.py
dreamai_ray/index/df.py
dreamai_ray/index/utils.py
dreamai_ray/pdf/__init__.py
dreamai_ray/pdf/app.py
dreamai_ray/pdf/df.py
dreamai_ray/pdf/extract.py
dreamai_ray/pdf/mappers.py
dreamai_ray/pdf/ner.py
dreamai_ray/pdf/utils.py
dreamai_ray-0.0.2.dist-info/LICENSE
dreamai_ray-0.0.2.dist-info/METADATA
dreamai_ray-0.0.2.dist-info/WHEEL
dreamai_ray-0.0.2.dist-info/entry_points.txt
dreamai_ray-0.0.2.dist-info/top_level.txt
dreamai_ray-0.0.2.dist-info/RECORD
