Metadata-Version: 2.1
Name: dreamai-ray
Version: 0.0.2
Summary: DreamAI platform leveraging RAY.
Home-page: https://github.com/HamzaFarhan/dreamai_ray
Author: Hamza Farhan
Author-email: thehamza96@gmail.com
License: Apache Software License 2.0
Keywords: nbdev jupyter notebook python
Classifier: Development Status :: 4 - Beta
Classifier: Intended Audience :: Developers
Classifier: Natural Language :: English
Classifier: Programming Language :: Python :: 3.8
Classifier: Programming Language :: Python :: 3.9
Classifier: Programming Language :: Python :: 3.10
Classifier: License :: OSI Approved :: Apache Software License
Requires-Python: >=3.8
License-File: LICENSE
Requires-Dist: ray[air]
Requires-Dist: dreamai
Requires-Dist: fastai
Requires-Dist: pypdf
Requires-Dist: redis
Requires-Dist: requests
Requires-Dist: sentence-transformers
Requires-Dist: setfit
Requires-Dist: setuptools
Requires-Dist: torch
Requires-Dist: transformers
Requires-Dist: wasabi
Requires-Dist: faiss-cpu
Provides-Extra: dev
